py3dbg/__init__.py
py3dbg/breakpoint.py
py3dbg/custom_module.py
py3dbg/defines.py
py3dbg/hardware_breakpoint.py
py3dbg/memory_breakpoint.py
py3dbg/memory_snapshot_block.py
py3dbg/memory_snapshot_context.py
py3dbg/my_ctypes.py
py3dbg/pdx.py
py3dbg/pydbg.py
py3dbg/pydbg_client.py
py3dbg/system_dll.py
py3dbg/windows_h.py
py3dbg-1.0.0.dist-info/METADATA
py3dbg-1.0.0.dist-info/WHEEL
py3dbg-1.0.0.dist-info/top_level.txt
py3dbg-1.0.0.dist-info/RECORD
