Metadata-Version: 2.1
Name: py3dbg
Version: 1.0.0
Summary: modified the PyDbg library to support x64 processes, enhancing its capabilities.
Home-page: https://github.com/qerogram/py3dbg
Author: Qerogram
Author-email: qerogram@google.com
License: UNKNOWN
Platform: UNKNOWN
Classifier: Programming Language :: Python :: 3
Classifier: License :: OSI Approved :: MIT License
Requires-Python: >=3.7
